buttersalt_ldap/__init__.py
buttersalt_ldap/ldap3.py
buttersalt_ldap/views.py
buttersalt_ldap/templates/ldap/account_detail.html
buttersalt_ldap/templates/ldap/account_edit.html
buttersalt_ldap/templates/ldap/index.html
buttersalt_ldap/templates/ldap/signup.html
buttersalt_ldap-1.2.0.dist-info/DESCRIPTION.rst
buttersalt_ldap-1.2.0.dist-info/METADATA
buttersalt_ldap-1.2.0.dist-info/RECORD
buttersalt_ldap-1.2.0.dist-info/WHEEL
buttersalt_ldap-1.2.0.dist-info/metadata.json
buttersalt_ldap-1.2.0.dist-info/top_level.txt
