Metadata-Version: 2.0
Name: buttersalt-ldap
Version: 1.2.0
Summary: LDAP management plugin
Home-page: https://github.com/lfzyx/ButterSalt-LDAP
Author: lfzyx
Author-email: lfzyx.me@gmail.com
License: MIT
Keywords: buttersalt ldap
Platform: UNKNOWN
Classifier: Development Status :: 4 - Beta
Classifier: Programming Language :: Python :: 3 :: Only
Classifier: Framework :: Flask
Classifier: License :: OSI Approved :: MIT License
Classifier: Topic :: Software Development :: Libraries :: Python Modules
Requires-Python: >=3.5.3
Requires-Dist: PyYAML
